twitch_chat_irc/__init__.py
twitch_chat_irc/__main__.py
twitch_chat_irc/twitch_chat_irc.py
twitch_chat_irc-0.0.4.dist-info/LICENSE
twitch_chat_irc-0.0.4.dist-info/METADATA
twitch_chat_irc-0.0.4.dist-info/WHEEL
twitch_chat_irc-0.0.4.dist-info/entry_points.txt
twitch_chat_irc-0.0.4.dist-info/top_level.txt
twitch_chat_irc-0.0.4.dist-info/RECORD
