Metadata-Version: 2.1
Name: twitch-chat-irc
Version: 0.0.4
Summary: A simple tool used to send and receive Twitch chat messages over IRC with python web sockets.
Home-page: https://github.com/scmanjarrez/twitch-chat-irc
Author: xenova, scmanjarrez
License: MIT
Keywords: python,twitch,irc,websockets
Platform: UNKNOWN
Classifier: License :: OSI Approved :: MIT License
Classifier: Programming Language :: Python :: 3
Classifier: Programming Language :: Python :: 3.8
Requires-Python: >= 3.7
License-File: LICENSE
Requires-Dist: python-decouple
Requires-Dist: emoji
